check_patroni/__init__.py
check_patroni/__main__.py
check_patroni/cli.py
check_patroni/cluster.py
check_patroni/convert.py
check_patroni/node.py
check_patroni/types.py
check_patroni-2.2.0.dist-info/LICENSE
check_patroni-2.2.0.dist-info/METADATA
check_patroni-2.2.0.dist-info/WHEEL
check_patroni-2.2.0.dist-info/entry_points.txt
check_patroni-2.2.0.dist-info/top_level.txt
check_patroni-2.2.0.dist-info/RECORD
