Metadata-Version: 2.1
Name: check-patroni
Version: 2.2.0
Summary: Nagios plugin to check on patroni
Home-page: https://github.com/dalibo/check_patroni
Author: Dalibo
Author-email: contact@dalibo.com
License: PostgreSQL
Keywords: patroni nagios check
Classifier: Development Status :: 5 - Production/Stable
Classifier: Environment :: Console
Classifier: License :: OSI Approved :: PostgreSQL License
Classifier: Programming Language :: Python :: 3
Classifier: Topic :: System :: Monitoring
Requires-Python: >=3.6
License-File: LICENSE
Requires-Dist: attrs!=21.1,>=17
Requires-Dist: requests
Requires-Dist: nagiosplugin>=1.3.2
Requires-Dist: click>=7.1
Provides-Extra: test
Requires-Dist: pytest>=6.0.2; extra == "test"
Requires-Dist: importlib-metadata; python_version < "3.8" and extra == "test"
